{"idCAM":["61aaa381-5a19-4b24-b38b-2cfa7b23214b"],"creator":["noID"],"projectCAM":["S2_CAM part 2"],"defocusCAM":[null],"date":[1702313253760],"nodes":[{"id":"9b73cc60-fe22-4e0c-bbe1-9599f62c44f6","value":10,"text":"Rettungsroboter","comment":"","position":{"x":650,"y":400},"isActive":true,"date":1702313254674,"kind":"Node","isSelected":false,"isConnectorSelected":false,"isDraggable":0,"isDeletable":0,"hasElementMoved":false,"eventLog":[{"time":1702313254674,"type":"create node","value":10}],"isTextChangeable":0},{"id":"2dfb60df-1b62-4484-80b7-1a5bddf33a2a","value":-3,"text":"Nachteile","comment":"","position":{"x":450,"y":400},"isActive":true,"date":1702313254674,"kind":"Node","isSelected":false,"isConnectorSelected":false,"isDraggable":0,"isDeletable":0,"hasElementMoved":false,"eventLog":[{"time":1702313254674,"type":"create node","value":-3}],"isTextChangeable":0},{"id":"cbb27ea9-ef85-4695-b558-88466adece16","value":3,"text":"Vorteile","comment":"","position":{"x":850,"y":400},"isActive":true,"date":1702313254674,"kind":"Node","isSelected":false,"isConnectorSelected":false,"isDraggable":0,"isDeletable":0,"hasElementMoved":false,"eventLog":[{"time":1702313254674,"type":"create node","value":3}],"isTextChangeable":0},{"id":"d13125c5-22a2-4cd5-9b13-8555ebd8b1b2","value":3,"text":"Einsatzort","comment":"","position":{"x":987.6667,"y":204.85},"isActive":true,"date":1702313254674,"kind":"Node","isSelected":false,"isConnectorSelected":false,"isDraggable":1,"isDeletable":1,"hasElementMoved":false,"eventLog":[{"time":"1702313254674","type":"create node","value":[3]},{"time":"2023-12-11T16:49:19.157Z","type":"position","value":{"x":[915.6667],"y":[208.85]}}],"isTextChangeable":1},{"id":"2f126d53-318b-4919-91f2-1da95c9b6458","value":-1,"text":"Zuverlässigkeit","comment":"fraglich; weicher Körper","position":{"x":440.6667,"y":223.85},"isActive":true,"date":1702313254674,"kind":"Node","isSelected":false,"isConnectorSelected":false,"isDraggable":1,"isDeletable":1,"hasElementMoved":false,"eventLog":[{"time":"1702313254674","type":"create node","value":[10]},{"time":"1702313392026","type":"selected","value":[true]},{"time":"1702313408607","type":"value","value":[-1]},{"time":"1702313408607","type":"comment","value":["fraglich; weicher Körper"]},{"time":"1702313408607","type":"selected","value":[false]},{"time":"2023-12-11T16:50:25.573Z","type":"position","value":{"x":[616.6667],"y":[229.85]}},{"time":"2023-12-11T16:50:25.707Z","type":"position","value":{"x":[461.6667],"y":[227.85]}}],"isTextChangeable":1},{"id":"60b3ba1c-01a2-4896-be94-41fa3f49919f","value":-2,"text":"Kosten","comment":"","position":{"x":202.6667,"y":262.85},"isActive":true,"date":1702313254675,"kind":"Node","isSelected":false,"isConnectorSelected":false,"isDraggable":1,"isDeletable":1,"hasElementMoved":false,"eventLog":[{"time":"1702313254675","type":"create node","value":[-3]},{"time":"1702313375679","type":"selected","value":[true]},{"time":"1702313378500","type":"value","value":[-2]},{"time":"1702313378500","type":"selected","value":[false]},{"time":"2023-12-11T16:50:24.457Z","type":"position","value":{"x":[439.6667],"y":[216.85]}},{"time":"2023-12-11T16:50:24.540Z","type":"position","value":{"x":[281.6667],"y":[246.85]}}],"isTextChangeable":1},{"id":"8bc2db88-c0ca-48a5-b780-741e8dba75e2","value":-3,"text":"Missbrauch","comment":"","position":{"x":279.6667,"y":624.85},"isActive":true,"date":1702313254675,"kind":"Node","isSelected":false,"isConnectorSelected":false,"isDraggable":1,"isDeletable":1,"hasElementMoved":false,"eventLog":[{"time":"1702313254675","type":"create node","value":[-3]},{"time":"2023-12-11T16:48:50.968Z","type":"position","value":{"x":[195.6667],"y":[420.85]}},{"time":"2023-12-11T16:50:22.156Z","type":"position","value":{"x":[216.6667],"y":[520.85]}}],"isTextChangeable":1},{"id":"add1bdc5-c5c6-4fda-97fb-735cd1cd94b8","value":3,"text":"Gefahr","comment":"","position":{"x":969.6667,"y":615.85},"isActive":true,"date":1702313254675,"kind":"Node","isSelected":false,"isConnectorSelected":false,"isDraggable":1,"isDeletable":1,"hasElementMoved":false,"eventLog":[{"time":1702313254675,"type":"create node","value":3}],"isTextChangeable":1},{"id":"f980a6d4-876f-422a-a0e1-91da0e68850f","value":-2,"text":"Entwicklungszeit","comment":"","position":{"x":153.6667,"y":463.85},"isActive":true,"date":1702313254675,"kind":"Node","isSelected":false,"isConnectorSelected":false,"isDraggable":1,"isDeletable":1,"hasElementMoved":false,"eventLog":[{"time":"1702313254675","type":"create node","value":[-2]},{"time":"2023-12-11T16:50:23.173Z","type":"position","value":{"x":[200.6667],"y":[279.85]}},{"time":"2023-12-11T16:50:23.574Z","type":"position","value":{"x":[154.6667],"y":[431.85]}}],"isTextChangeable":1},{"id":"3c14b592-bbcd-46fe-84bb-d8fb3ddaf5c6","value":10,"text":"Fähigkeit","comment":"","position":{"x":720.6667,"y":591.85},"isActive":true,"date":1702313254675,"kind":"Node","isSelected":false,"isConnectorSelected":false,"isDraggable":1,"isDeletable":1,"hasElementMoved":false,"eventLog":[{"time":"1702313254675","type":"create node","value":[10]},{"time":"2023-12-11T16:50:17.222Z","type":"position","value":{"x":[665.6667],"y":[601.85]}},{"time":"2023-12-11T16:50:19.590Z","type":"position","value":{"x":[726.6667],"y":[601.85]}}],"isTextChangeable":1},{"id":"ed78245f-524b-4248-90da-2a1da4fac2c4","value":10,"text":"Autonomie","comment":"teilweise ferngesteuert","position":{"x":560.6667,"y":590.85},"isActive":true,"date":1702313254675,"kind":"Node","isSelected":false,"isConnectorSelected":false,"isDraggable":1,"isDeletable":1,"hasElementMoved":false,"eventLog":[{"time":"1702313254675","type":"create node","value":[-2]},{"time":"1702313269819","type":"selected","value":[true]},{"time":"1702313286133","type":"text","value":["Autonomie"]},{"time":"1702313286133","type":"value","value":[10]},{"time":"1702313286133","type":"comment","value":["teilweise ferngesteuert"]},{"time":"1702313286133","type":"selected","value":[false]},{"time":"2023-12-11T16:48:16.184Z","type":"position","value":{"x":[264.6667],"y":[581.85]}},{"time":"2023-12-11T16:48:16.267Z","type":"position","value":{"x":[449.6667],"y":[572.85]}},{"time":"1702313305472","type":"selected","value":[true]},{"time":"1702313306760","type":"selected","value":[false]},{"time":"2023-12-11T16:48:39.635Z","type":"position","value":{"x":[478.6667],"y":[566.85]}},{"time":"2023-12-11T16:50:14.639Z","type":"position","value":{"x":[489.6667],"y":[591.85]}},{"time":"2023-12-11T16:50:18.392Z","type":"position","value":{"x":[478.6667],"y":[593.85]}}],"isTextChangeable":1},{"id":"6fdf228e-5e75-4cc4-b4b2-fa49b9ac22f8","value":3,"text":"Notfallversorgung","comment":"","position":{"x":1128.6667,"y":272.85},"isActive":true,"date":1702313254675,"kind":"Node","isSelected":false,"isConnectorSelected":false,"isDraggable":1,"isDeletable":1,"hasElementMoved":false,"eventLog":[{"time":1702313254675,"type":"create node","value":3}],"isTextChangeable":1},{"id":"a1e363f3-c55c-4f6f-ac3d-4103d780bf72","value":2,"text":"Sammlung von Daten","comment":"","position":{"x":1082.6667,"y":441.85},"isActive":true,"date":1702313254675,"kind":"Node","isSelected":false,"isConnectorSelected":false,"isDraggable":1,"isDeletable":1,"hasElementMoved":false,"eventLog":[{"time":1702313254675,"type":"create node","value":3},{"time":1702313369957,"type":"selected","value":1},{"time":1702313371568,"type":"value","value":2},{"time":1702313371568,"type":"selected","value":0}],"isTextChangeable":1},{"id":"1bcfb1e4-ef2c-4ef9-9795-8efb81d3941c","value":0,"text":"","comment":"","position":{"x":782.6667,"y":182.85},"isActive":false,"date":1702313258119,"kind":"Node","isSelected":false,"isConnectorSelected":false,"isDraggable":1,"isDeletable":1,"hasElementMoved":false,"eventLog":[{"time":1702313258119,"type":"create node","value":0},{"time":1702313293961,"type":"selected","value":1},{"time":1702313295045,"type":"node was deleted","value":-99}],"isTextChangeable":1},{"id":"9ad4841e-18ff-4184-835c-e17dfc7ce4e0","value":2,"text":"Anpassung","comment":"durch weichen Körper","position":{"x":850.6667,"y":171.85},"isActive":true,"date":1702313336260,"kind":"Node","isSelected":false,"isConnectorSelected":false,"isDraggable":1,"isDeletable":1,"hasElementMoved":false,"eventLog":[{"time":"1702313336260","type":"create node","value":[0]},{"time":"1702313336345","type":"selected","value":[true]},{"time":"1702313357397","type":"text","value":["Anpassung"]},{"time":"1702313357397","type":"value","value":[3]},{"time":"1702313357397","type":"comment","value":["durch weichen Körper"]},{"time":"1702313357397","type":"selected","value":[false]},{"time":"2023-12-11T16:49:18.270Z","type":"position","value":{"x":[1024.6667],"y":[111.85]}},{"time":"2023-12-11T16:49:18.419Z","type":"position","value":{"x":[871.6667],"y":[148.85]}},{"time":"2023-12-11T16:49:19.770Z","type":"position","value":{"x":[794.6667],"y":[160.85]}},{"time":"1702313383512","type":"selected","value":[true]},{"time":"1702313385486","type":"value","value":[2]},{"time":"1702313385486","type":"selected","value":[false]}],"isTextChangeable":1}],"connectors":[{"id":"51c15f6d-cb25-4917-9263-0c9da843bfe0","source":"9b73cc60-fe22-4e0c-bbe1-9599f62c44f6","target":"2dfb60df-1b62-4484-80b7-1a5bddf33a2a","agreement":true,"isActive":true,"date":1702313254675,"kind":"Connector","isSelected":false,"intensity":3,"isDeletable":false,"isOver":false,"isBidirectional":false,"eventLog":[{"time":1702313254675,"type":"create connection"}]},{"id":"1dba30df-932f-4c95-bad6-49451f717db7","source":"9b73cc60-fe22-4e0c-bbe1-9599f62c44f6","target":"cbb27ea9-ef85-4695-b558-88466adece16","agreement":true,"isActive":true,"date":1702313254675,"kind":"Connector","isSelected":false,"intensity":3,"isDeletable":true,"isOver":false,"isBidirectional":false,"eventLog":[{"time":1702313254675,"type":"create connection"}]},{"id":"ce051154-9bae-4f02-bcc2-5ad33025b5c4","source":"d13125c5-22a2-4cd5-9b13-8555ebd8b1b2","target":"cbb27ea9-ef85-4695-b558-88466adece16","agreement":true,"isActive":true,"date":1702313254675,"kind":"Connector","isSelected":false,"intensity":9,"isDeletable":true,"isOver":false,"isBidirectional":false,"eventLog":[{"time":1702313254675,"type":"create connection"}]},{"id":"c7ba91aa-5174-4cb8-aaca-698493b2bea9","source":"2f126d53-318b-4919-91f2-1da95c9b6458","target":"2dfb60df-1b62-4484-80b7-1a5bddf33a2a","agreement":true,"isActive":true,"date":1702313254675,"kind":"Connector","isSelected":false,"intensity":3,"isDeletable":true,"isOver":false,"isBidirectional":false,"eventLog":[{"time":1702313254675,"type":"create connection"}]},{"id":"ecc1db55-5d73-45a5-ae3f-3138dcdb8153","source":"2f126d53-318b-4919-91f2-1da95c9b6458","target":"cbb27ea9-ef85-4695-b558-88466adece16","agreement":true,"isActive":false,"date":1702313254675,"kind":"Connector","isSelected":false,"intensity":3,"isDeletable":true,"isOver":false,"isBidirectional":false,"eventLog":[{"time":1702313254675,"type":"create connection"},{"time":1702313409848,"type":"selected","value":1},{"time":1702313410937,"type":"connector was deleted","value":-99},{"time":1702313410937,"type":"active","value":0}]},{"id":"22854ea6-e9a0-4e68-adce-5581d76bbe21","source":"60b3ba1c-01a2-4896-be94-41fa3f49919f","target":"2dfb60df-1b62-4484-80b7-1a5bddf33a2a","agreement":true,"isActive":true,"date":1702313254675,"kind":"Connector","isSelected":false,"intensity":9,"isDeletable":true,"isOver":false,"isBidirectional":false,"eventLog":[{"time":1702313254675,"type":"create connection"}]},{"id":"cd5acbbb-7d7b-4723-9463-746929c64634","source":"8bc2db88-c0ca-48a5-b780-741e8dba75e2","target":"2dfb60df-1b62-4484-80b7-1a5bddf33a2a","agreement":true,"isActive":true,"date":1702313254675,"kind":"Connector","isSelected":false,"intensity":9,"isDeletable":true,"isOver":false,"isBidirectional":false,"eventLog":[{"time":1702313254675,"type":"create connection"}]},{"id":"7f204feb-ab5d-4da4-bb96-c4e51483921a","source":"cbb27ea9-ef85-4695-b558-88466adece16","target":"add1bdc5-c5c6-4fda-97fb-735cd1cd94b8","agreement":true,"isActive":true,"date":1702313254675,"kind":"Connector","isSelected":false,"intensity":9,"isDeletable":true,"isOver":false,"isBidirectional":false,"eventLog":[{"time":1702313254675,"type":"create connection"}]},{"id":"4bee89c5-feea-412f-9670-6829c87812c5","source":"2dfb60df-1b62-4484-80b7-1a5bddf33a2a","target":"f980a6d4-876f-422a-a0e1-91da0e68850f","agreement":true,"isActive":true,"date":1702313254675,"kind":"Connector","isSelected":false,"intensity":9,"isDeletable":true,"isOver":false,"isBidirectional":false,"eventLog":[{"time":1702313254675,"type":"create connection"}]},{"id":"522d4896-108a-4986-a628-11f6d2704ded","source":"2dfb60df-1b62-4484-80b7-1a5bddf33a2a","target":"3c14b592-bbcd-46fe-84bb-d8fb3ddaf5c6","agreement":true,"isActive":true,"date":1702313254675,"kind":"Connector","isSelected":false,"intensity":3,"isDeletable":true,"isOver":false,"isBidirectional":false,"eventLog":[{"time":1702313254675,"type":"create connection"}]},{"id":"ad4d695d-e81c-48e2-908b-6cd2a9e7f4ff","source":"cbb27ea9-ef85-4695-b558-88466adece16","target":"3c14b592-bbcd-46fe-84bb-d8fb3ddaf5c6","agreement":true,"isActive":true,"date":1702313254675,"kind":"Connector","isSelected":false,"intensity":3,"isDeletable":true,"isOver":false,"isBidirectional":false,"eventLog":[{"time":1702313254675,"type":"create connection"}]},{"id":"7326df2f-5ed0-47b8-a331-e5fb2e3fe235","source":"ed78245f-524b-4248-90da-2a1da4fac2c4","target":"2dfb60df-1b62-4484-80b7-1a5bddf33a2a","agreement":true,"isActive":true,"date":1702313254675,"kind":"Connector","isSelected":false,"intensity":3,"isDeletable":true,"isOver":false,"isBidirectional":false,"eventLog":[{"time":1702313254675,"type":"create connection"},{"time":1702313289135,"type":"selected","value":1},{"time":1702313289550,"type":"change intensity of connector","value":9},{"time":1702313289550,"type":"selected","value":0},{"time":1702313291865,"type":"selected","value":1},{"time":1702313293164,"type":"connector was deleted","value":-99},{"time":1702313293164,"type":"active","value":0},{"time":1702313312230,"type":"selected","value":1},{"time":1702313312635,"type":"change intensity of connector","value":9},{"time":1702313312635,"type":"selected","value":0},{"time":1702313313982,"type":"selected","value":1},{"time":1702313317167,"type":"change intensity of connector","value":3},{"time":1702313317167,"type":"selected","value":0}]},{"id":"ef377047-5979-4e16-8c42-76e816275a29","source":"6fdf228e-5e75-4cc4-b4b2-fa49b9ac22f8","target":"cbb27ea9-ef85-4695-b558-88466adece16","agreement":true,"isActive":true,"date":1702313254675,"kind":"Connector","isSelected":false,"intensity":9,"isDeletable":true,"isOver":false,"isBidirectional":false,"eventLog":[{"time":1702313254675,"type":"create connection"}]},{"id":"87cf2d84-e615-4597-b888-d8146bb23509","source":"cbb27ea9-ef85-4695-b558-88466adece16","target":"a1e363f3-c55c-4f6f-ac3d-4103d780bf72","agreement":true,"isActive":true,"date":1702313254675,"kind":"Connector","isSelected":false,"intensity":9,"isDeletable":true,"isOver":false,"isBidirectional":false,"eventLog":[{"time":1702313254675,"type":"create connection"}]},{"id":"d766f2c0-02d9-4c27-9884-d97d58ea0988","source":"9b73cc60-fe22-4e0c-bbe1-9599f62c44f6","target":"ed78245f-524b-4248-90da-2a1da4fac2c4","agreement":true,"isActive":false,"date":1702313299440,"kind":"Connector","isSelected":false,"intensity":3,"isDeletable":true,"isOver":false,"isBidirectional":false,"eventLog":[{"time":1702313299440,"type":"create connection"},{"time":1702313302370,"type":"selected","value":1},{"time":1702313303678,"type":"connector was deleted","value":-99},{"time":1702313303678,"type":"active","value":0}]},{"id":"9d39a8cb-f99f-427e-b049-83668a21d3cd","source":"cbb27ea9-ef85-4695-b558-88466adece16","target":"ed78245f-524b-4248-90da-2a1da4fac2c4","agreement":true,"isActive":true,"date":1702313311145,"kind":"Connector","isSelected":false,"intensity":3,"isDeletable":true,"isOver":false,"isBidirectional":false,"eventLog":[{"time":1702313311145,"type":"create connection"}]},{"id":"27cc14d1-9bc2-46ca-8089-0426d5f9f19a","source":"9ad4841e-18ff-4184-835c-e17dfc7ce4e0","target":"cbb27ea9-ef85-4695-b558-88466adece16","agreement":true,"isActive":true,"date":1702313361191,"kind":"Connector","isSelected":false,"intensity":9,"isDeletable":true,"isOver":false,"isBidirectional":false,"eventLog":[{"time":1702313361191,"type":"create connection"},{"time":1702313362167,"type":"selected","value":1},{"time":1702313369626,"type":"change intensity of connector","value":9},{"time":1702313369626,"type":"selected","value":0}]}],"currentID":{},"currentNode":{},"hasSelectedNode":[false],"currentConnector":{},"hasSelectedConnector":[false],"readyToMove":[false],"isIncoming":[false],"hasElementMoved":[false]}
