{"idCAM":["a9884810-f6bf-41cd-88e3-7da3d7fe3fef"],"creator":["noID"],"projectCAM":["CAMspiracy t2 Germany CAM"],"defocusCAM":[],"date":[1702330377832],"nodes":[{"id":"da4f9aa4-42dd-4950-8131-c3d52d8381cc","value":-2,"text":"Klimawandel","comment":"","position":{"x":650,"y":400},"isActive":true,"date":1702330378671,"kind":"Node","isSelected":false,"isConnectorSelected":true,"isDraggable":0,"isDeletable":0,"hasElementMoved":false,"eventLog":[{"time":1702330378671,"type":"create node","value":0},{"time":1702330653243,"type":"selected","value":1},{"time":1702330656622,"type":"value","value":-2},{"time":1702330656622,"type":"selected","value":0}],"isTextChangeable":0},{"id":"43fe5882-6daf-4f95-be8e-9ef642440c4c","value":-2,"text":"Artensterben","comment":"","position":{"x":900.8889,"y":549.3333},"isActive":true,"date":1702330397443,"kind":"Node","isSelected":false,"isConnectorSelected":false,"isDraggable":1,"isDeletable":1,"hasElementMoved":false,"eventLog":[{"time":"1702330397443","type":"create node","value":[0]},{"time":"1702330397651","type":"selected","value":[true]},{"time":"1702330406932","type":"text","value":["Artensterben"]},{"time":"1702330406932","type":"value","value":[-3]},{"time":"1702330406932","type":"selected","value":[false]},{"time":"2023-12-11T21:34:06.728Z","type":"position","value":{"x":[802.8889],"y":[473.3333]}},{"time":"2023-12-11T21:34:57.147Z","type":"position","value":{"x":[926.8889],"y":[448.3333]}},{"time":"2023-12-11T21:35:00.435Z","type":"position","value":{"x":[940.8889],"y":[474.3333]}},{"time":"2023-12-11T21:35:32.066Z","type":"position","value":{"x":[969.8889],"y":[498.3333]}},{"time":"1702330643244","type":"selected","value":[true]},{"time":"1702330645261","type":"value","value":[-2]},{"time":"1702330645261","type":"selected","value":[false]},{"time":"2023-12-11T21:42:10.685Z","type":"position","value":{"x":[938.8889],"y":[543.3333]}}],"isTextChangeable":1},{"id":"f0287fc0-45ba-4857-b146-a7859af80ee8","value":-2,"text":"Umweltkatastrophen","comment":"","position":{"x":823.8889,"y":259.3333},"isActive":true,"date":1702330407864,"kind":"Node","isSelected":false,"isConnectorSelected":false,"isDraggable":1,"isDeletable":1,"hasElementMoved":false,"eventLog":[{"time":"1702330407864","type":"create node","value":[0]},{"time":"1702330408040","type":"selected","value":[true]},{"time":"1702330416082","type":"text","value":["Umweltkatastrophen"]},{"time":"1702330416082","type":"value","value":[-3]},{"time":"1702330416082","type":"selected","value":[false]},{"time":"2023-12-11T21:33:48.018Z","type":"position","value":{"x":[893.8889],"y":[358.3333]}},{"time":"2023-12-11T21:35:29.864Z","type":"position","value":{"x":[861.8889],"y":[253.3333]}},{"time":"1702330639591","type":"selected","value":[true]},{"time":"1702330641296","type":"value","value":[-2]},{"time":"1702330641296","type":"selected","value":[false]}],"isTextChangeable":1},{"id":"a1eec96f-94eb-47f0-a810-c48827d16ede","value":-1,"text":"Dürren","comment":"","position":{"x":909.8889,"y":365.3333},"isActive":true,"date":1702330417330,"kind":"Node","isSelected":false,"isConnectorSelected":false,"isDraggable":1,"isDeletable":1,"hasElementMoved":false,"eventLog":[{"time":"1702330417330","type":"create node","value":[0]},{"time":"1702330417506","type":"selected","value":[true]},{"time":"1702330426707","type":"text","value":["Dürren"]},{"time":"1702330426707","type":"value","value":[-3]},{"time":"1702330426707","type":"selected","value":[false]},{"time":"2023-12-11T21:34:03.967Z","type":"position","value":{"x":[896.8889],"y":[543.3333]}},{"time":"2023-12-11T21:34:55.825Z","type":"position","value":{"x":[822.8889],"y":[586.3333]}},{"time":"2023-12-11T21:34:59.118Z","type":"position","value":{"x":[815.8889],"y":[584.3333]}},{"time":"1702330502698","type":"selected","value":[true]},{"time":"1702330520411","type":"selected","value":[false]},{"time":"2023-12-11T21:35:25.402Z","type":"position","value":{"x":[825.8889],"y":[578.3333]}},{"time":"2023-12-11T21:35:25.780Z","type":"position","value":{"x":[875.8889],"y":[392.3333]}},{"time":"2023-12-11T21:35:37.865Z","type":"position","value":{"x":[911.8889],"y":[357.3333]}},{"time":"1702330636121","type":"selected","value":[true]},{"time":"1702330638359","type":"value","value":[-1]},{"time":"1702330638359","type":"selected","value":[false]},{"time":"1702330907338","type":"selected","value":[true]},{"time":"1702330908251","type":"selected","value":[false]}],"isTextChangeable":1},{"id":"630c66a7-3fa6-48c4-ae80-b371aaa134b2","value":-2,"text":"Flut","comment":"","position":{"x":963.8889,"y":251.3333},"isActive":true,"date":1702330429040,"kind":"Node","isSelected":false,"isConnectorSelected":false,"isDraggable":1,"isDeletable":1,"hasElementMoved":false,"eventLog":[{"time":"1702330429040","type":"create node","value":[0]},{"time":"1702330429210","type":"selected","value":[true]},{"time":"1702330434653","type":"text","value":["Flut"]},{"time":"1702330434653","type":"value","value":[-3]},{"time":"1702330434653","type":"selected","value":[false]},{"time":"2023-12-11T21:35:34.183Z","type":"position","value":{"x":[1027.8889],"y":[281.3333]}},{"time":"1702330631777","type":"selected","value":[true]},{"time":"1702330634758","type":"value","value":[-2]},{"time":"1702330634758","type":"selected","value":[false]},{"time":"2023-12-11T21:42:05.128Z","type":"position","value":{"x":[983.8889],"y":[253.3333]}}],"isTextChangeable":1},{"id":"83bab52f-e277-4b0a-873e-d18b310c6265","value":-1,"text":"Stürme","comment":"","position":{"x":887.8889,"y":166.3333},"isActive":true,"date":1702330435928,"kind":"Node","isSelected":false,"isConnectorSelected":false,"isDraggable":1,"isDeletable":1,"hasElementMoved":false,"eventLog":[{"time":"1702330435928","type":"create node","value":[0]},{"time":"1702330437170","type":"selected","value":[true]},{"time":"1702330442410","type":"text","value":["Stürme"]},{"time":"1702330442410","type":"value","value":[-3]},{"time":"1702330442410","type":"selected","value":[false]},{"time":"2023-12-11T21:35:35.554Z","type":"position","value":{"x":[963.8889],"y":[143.3333]}},{"time":"1702330628908","type":"selected","value":[true]},{"time":"1702330630896","type":"value","value":[-1]},{"time":"1702330630896","type":"selected","value":[false]},{"time":"2023-12-11T21:41:59.130Z","type":"position","value":{"x":[894.8889],"y":[178.3333]}},{"time":"1702330920095","type":"selected","value":[true]},{"time":"1702330920905","type":"selected","value":[false]}],"isTextChangeable":1},{"id":"4d2c1400-6476-4628-95eb-b2aaf0660ef4","value":-3,"text":"Veränderung Flora &Fauna","comment":"","position":{"x":802.8889,"y":468.3333},"isActive":true,"date":1702330448685,"kind":"Node","isSelected":false,"isConnectorSelected":true,"isDraggable":1,"isDeletable":1,"hasElementMoved":false,"eventLog":[{"time":"1702330448685","type":"create node","value":[0]},{"time":"1702330448883","type":"selected","value":[true]},{"time":"1702330480154","type":"text","value":["Veränderung Flora &Fauna"]},{"time":"1702330480154","type":"selected","value":[false]},{"time":"1702330482884","type":"selected","value":[true]},{"time":"1702330485956","type":"selected","value":[false]},{"time":"1702330487368","type":"selected","value":[true]},{"time":"1702330489957","type":"value","value":[-3]},{"time":"1702330489957","type":"selected","value":[false]},{"time":"2023-12-11T21:34:53.396Z","type":"position","value":{"x":[780.8889],"y":[481.3333]}}],"isTextChangeable":1},{"id":"74db7644-2a90-4340-b315-46b7b4ebfc92","value":-3,"text":"Verarmung","comment":"Lebensgrundlage von Bauern könnte zerstört werden","position":{"x":324.8889,"y":364.3333},"isActive":true,"date":1702330542416,"kind":"Node","isSelected":false,"isConnectorSelected":false,"isDraggable":1,"isDeletable":1,"hasElementMoved":false,"eventLog":[{"time":"1702330542416","type":"create node","value":[0]},{"time":"1702330542612","type":"selected","value":[true]},{"time":"1702330568067","type":"text","value":["Verarmung"]},{"time":"1702330568067","type":"value","value":[-3]},{"time":"1702330568067","type":"comment","value":["Lebensgrundlage von Bauern könnte zerstört werden"]},{"time":"1702330568067","type":"selected","value":[false]},{"time":"1702330623639","type":"selected","value":[true]},{"time":"1702330628008","type":"selected","value":[false]},{"time":"1702330650647","type":"selected","value":[true]},{"time":"1702330651982","type":"selected","value":[false]},{"time":"2023-12-11T21:39:13.533Z","type":"position","value":{"x":[370.8889],"y":[302.3333]}}],"isTextChangeable":1},{"id":"835e780e-58f4-46a0-9107-9590f4ee648e","value":-2,"text":"Soziale Spannungen","comment":"","position":{"x":334.8889,"y":497.3333},"isActive":true,"date":1702330575580,"kind":"Node","isSelected":false,"isConnectorSelected":false,"isDraggable":1,"isDeletable":1,"hasElementMoved":false,"eventLog":[{"time":1702330575580,"type":"create node","value":"0"},{"time":1702330575747,"type":"selected","value":"TRUE"},{"time":1702330611226,"type":"text","value":"Soziale Spannungen"},{"time":1702330611226,"type":"value","value":"-3"},{"time":1702330611226,"type":"selected","value":"FALSE"},{"time":1702330646924,"type":"selected","value":"TRUE"},{"time":1702330648953,"type":"value","value":"-2"},{"time":1702330648953,"type":"selected","value":"FALSE"}],"isTextChangeable":1},{"id":"22dd6e1f-3f92-4e07-b581-e40720c9370e","value":2,"text":"Technologische Innovationen","comment":"","position":{"x":490.8889,"y":200.3333},"isActive":true,"date":1702330666999,"kind":"Node","isSelected":false,"isConnectorSelected":false,"isDraggable":1,"isDeletable":1,"hasElementMoved":false,"eventLog":[{"time":"1702330666999","type":"create node","value":[0]},{"time":"1702330667204","type":"selected","value":[true]},{"time":"1702330682933","type":"text","value":["Schnellerer technologischer Fortschritt"]},{"time":"1702330682933","type":"value","value":[3]},{"time":"1702330682933","type":"selected","value":[false]},{"time":"1702330704034","type":"selected","value":[true]},{"time":"1702330714362","type":"text","value":["Technologische Innovationen"]},{"time":"1702330714362","type":"selected","value":[false]},{"time":"2023-12-11T21:38:35.484Z","type":"position","value":{"x":[567.8889],"y":[213.3333]}},{"time":"2023-12-11T21:38:54.066Z","type":"position","value":{"x":[515.8889],"y":[230.3333]}},{"time":"2023-12-11T21:41:06.607Z","type":"position","value":{"x":[498.8889],"y":[210.3333]}},{"time":"1702330867447","type":"selected","value":[true]},{"time":"1702330868612","type":"selected","value":[false]},{"time":"1702330870721","type":"selected","value":[true]},{"time":"1702330874667","type":"value","value":[2]},{"time":"1702330874667","type":"selected","value":[false]}],"isTextChangeable":1},{"id":"c863aedb-a0c1-4ba1-a14e-d0f89ad35279","value":2,"text":"Fortschritt","comment":"","position":{"x":632.8889,"y":273.3333},"isActive":true,"date":1702330685302,"kind":"Node","isSelected":false,"isConnectorSelected":false,"isDraggable":1,"isDeletable":1,"hasElementMoved":false,"eventLog":[{"time":"1702330685302","type":"create node","value":[0]},{"time":"1702330685478","type":"selected","value":[true]},{"time":"1702330701108","type":"text","value":["Fortschritt"]},{"time":"1702330701108","type":"value","value":[3]},{"time":"1702330701108","type":"selected","value":[false]},{"time":"2023-12-11T21:38:22.301Z","type":"position","value":{"x":[651.8889],"y":[156.3333]}},{"time":"1702330728245","type":"selected","value":[true]},{"time":"1702330730799","type":"value","value":[2]},{"time":"1702330730799","type":"selected","value":[false]},{"time":"2023-12-11T21:38:52.549Z","type":"position","value":{"x":[625.8889],"y":[264.3333]}},{"time":"2023-12-11T21:40:54.222Z","type":"position","value":{"x":[616.8889],"y":[327.3333]}},{"time":"1702330886418","type":"selected","value":[true]},{"time":"1702330888569","type":"selected","value":[false]}],"isTextChangeable":1},{"id":"df1ffb70-3ec8-4157-a806-01a001632d59","value":1,"text":"Überdenkung von Konzepten","comment":"","position":{"x":730.8889,"y":173.3333},"isActive":true,"date":1702330716781,"kind":"Node","isSelected":false,"isConnectorSelected":false,"isDraggable":1,"isDeletable":1,"hasElementMoved":false,"eventLog":[{"time":"1702330716781","type":"create node","value":[0]},{"time":"1702330716946","type":"selected","value":[true]},{"time":"1702330726659","type":"text","value":["Überdenkung von Konzepten"]},{"time":"1702330726659","type":"value","value":[1]},{"time":"1702330726659","type":"selected","value":[false]},{"time":"2023-12-11T21:38:55.340Z","type":"position","value":{"x":[677.8889],"y":[179.3333]}},{"time":"1702330883919","type":"selected","value":[true]},{"time":"1702330884799","type":"selected","value":[false]},{"time":"2023-12-11T21:41:33.978Z","type":"position","value":{"x":[716.8889],"y":[215.3333]}}],"isTextChangeable":1},{"id":"538b66d8-0024-419d-8b18-854e9258d7aa","value":1,"text":"Erhöhtes Umweltbewusstsein","comment":"","position":{"x":610.8889,"y":148.3333},"isActive":true,"date":1702330737539,"kind":"Node","isSelected":false,"isConnectorSelected":false,"isDraggable":1,"isDeletable":1,"hasElementMoved":false,"eventLog":[{"time":1702330737539,"type":"create node","value":"0"},{"time":1702330737704,"type":"selected","value":"TRUE"},{"time":1702330748786,"type":"text","value":"Erhöhtes Umweltbewusstsein"},{"time":1702330748786,"type":"selected","value":"FALSE"},{"time":1702330749830,"type":"selected","value":"TRUE"},{"time":1702330752090,"type":"value","value":"1"},{"time":1702330752090,"type":"selected","value":"FALSE"},{"time":1702330875629,"type":"selected","value":"TRUE"},{"time":1702330877206,"type":"selected","value":"FALSE"}],"isTextChangeable":1},{"id":"5415d993-c942-4b91-8f1e-5e9ed7f6b5ee","value":-2,"text":"Auswirkungen auf Menschen","comment":"","position":{"x":450.8889,"y":406.3333},"isActive":true,"date":1702330755856,"kind":"Node","isSelected":false,"isConnectorSelected":false,"isDraggable":1,"isDeletable":1,"hasElementMoved":false,"eventLog":[{"time":1702330755856,"type":"create node","value":"0"},{"time":1702330756042,"type":"selected","value":"TRUE"},{"time":1702330769903,"type":"text","value":"Auswirkungen auf Menschen"},{"time":1702330769903,"type":"value","value":"-2"},{"time":1702330769903,"type":"selected","value":"FALSE"},{"time":1702330834911,"type":"selected","value":"TRUE"},{"time":1702330836758,"type":"selected","value":"FALSE"},{"time":1702330839704,"type":"selected","value":"TRUE"},{"time":1702330843777,"type":"selected","value":"FALSE"}],"isTextChangeable":1}],"connectors":[{"id":"a8a9a70f-3103-4386-a6aa-3b92728024de","source":"74db7644-2a90-4340-b315-46b7b4ebfc92","target":"5415d993-c942-4b91-8f1e-5e9ed7f6b5ee","agreement":true,"isActive":true,"date":1702330772422,"kind":"Connector","isSelected":false,"intensity":6,"isDeletable":true,"isOver":false,"isBidirectional":false,"eventLog":[{"time":1702330772422,"type":"create connection"},{"time":1702330828778,"type":"selected","value":1},{"time":1702330833075,"type":"change intensity of connector","value":9},{"time":1702330833075,"type":"selected","value":0},{"time":1702330850547,"type":"selected","value":1},{"time":1702330852879,"type":"change intensity of connector","value":6},{"time":1702330852879,"type":"selected","value":0}]},{"id":"1165acb2-56b5-4ab0-a4d3-6d741cd9f4c0","source":"835e780e-58f4-46a0-9107-9590f4ee648e","target":"5415d993-c942-4b91-8f1e-5e9ed7f6b5ee","agreement":true,"isActive":true,"date":1702330773776,"kind":"Connector","isSelected":false,"intensity":6,"isDeletable":true,"isOver":false,"isBidirectional":false,"eventLog":[{"time":1702330773776,"type":"create connection"},{"time":1702330775183,"type":"selected","value":1},{"time":1702330786768,"type":"change intensity of connector","value":-9},{"time":1702330786768,"type":"selected","value":0},{"time":1702330788375,"type":"selected","value":1},{"time":1702330791638,"type":"change intensity of connector","value":-9},{"time":1702330791638,"type":"selected","value":0},{"time":1702330791831,"type":"selected","value":1},{"time":1702330804288,"type":"change intensity of connector","value":-9},{"time":1702330804288,"type":"selected","value":0},{"time":1702330825547,"type":"selected","value":1},{"time":1702330827680,"type":"change intensity of connector","value":9},{"time":1702330827680,"type":"selected","value":0},{"time":1702330847706,"type":"selected","value":1},{"time":1702330849251,"type":"change intensity of connector","value":6},{"time":1702330849251,"type":"selected","value":0}]},{"id":"28891b90-27f5-4d3d-bbd5-4b182fe27675","source":"da4f9aa4-42dd-4950-8131-c3d52d8381cc","target":"5415d993-c942-4b91-8f1e-5e9ed7f6b5ee","agreement":true,"isActive":true,"date":1702330839476,"kind":"Connector","isSelected":false,"intensity":6,"isDeletable":true,"isOver":false,"isBidirectional":false,"eventLog":[{"time":1702330839476,"type":"create connection"},{"time":1702330843961,"type":"selected","value":1},{"time":1702330846193,"type":"change intensity of connector","value":6},{"time":1702330846193,"type":"selected","value":0}]},{"id":"92512645-223e-49d6-902a-a32790333f47","source":"c863aedb-a0c1-4ba1-a14e-d0f89ad35279","target":"da4f9aa4-42dd-4950-8131-c3d52d8381cc","agreement":true,"isActive":true,"date":1702330856083,"kind":"Connector","isSelected":false,"intensity":3,"isDeletable":true,"isOver":false,"isBidirectional":false,"eventLog":[{"time":1702330856083,"type":"create connection"},{"time":1702330857050,"type":"selected","value":1},{"time":1702330865316,"type":"change intensity of connector","value":6},{"time":1702330865316,"type":"selected","value":0},{"time":1702330903536,"type":"selected","value":1},{"time":1702330906003,"type":"change intensity of connector","value":3},{"time":1702330906003,"type":"selected","value":0}]},{"id":"80312fa2-d325-4481-b50b-58ed89a1e07e","source":"c863aedb-a0c1-4ba1-a14e-d0f89ad35279","target":"22dd6e1f-3f92-4e07-b581-e40720c9370e","agreement":true,"isActive":true,"date":1702330870565,"kind":"Connector","isSelected":false,"intensity":6,"isDeletable":true,"isOver":false,"isBidirectional":false,"eventLog":[{"time":1702330870565,"type":"create connection"},{"time":1702330895646,"type":"selected","value":1},{"time":1702330898792,"type":"change intensity of connector","value":6},{"time":1702330898792,"type":"selected","value":0}]},{"id":"ab6ab506-6142-4396-90e3-3e9cdecdced0","source":"c863aedb-a0c1-4ba1-a14e-d0f89ad35279","target":"538b66d8-0024-419d-8b18-854e9258d7aa","agreement":true,"isActive":true,"date":1702330878546,"kind":"Connector","isSelected":false,"intensity":3,"isDeletable":true,"isOver":false,"isBidirectional":false,"eventLog":[{"time":1702330878546,"type":"create connection"},{"time":1702330880010,"type":"selected","value":1},{"time":1702330881536,"type":"change intensity of connector","value":6},{"time":1702330881536,"type":"selected","value":0},{"time":1702330899959,"type":"selected","value":1},{"time":1702330902062,"type":"change intensity of connector","value":3},{"time":1702330902062,"type":"selected","value":0}]},{"id":"be081b55-5dfb-4c49-abb9-ae30a94265b9","source":"df1ffb70-3ec8-4157-a806-01a001632d59","target":"c863aedb-a0c1-4ba1-a14e-d0f89ad35279","agreement":true,"isActive":true,"date":1702330889823,"kind":"Connector","isSelected":false,"intensity":3,"isDeletable":true,"isOver":false,"isBidirectional":false,"eventLog":[{"time":1702330889823,"type":"create connection"},{"time":1702330891040,"type":"selected","value":1},{"time":1702330893255,"type":"change intensity of connector","value":3},{"time":1702330893255,"type":"selected","value":0}]},{"id":"1c958828-9370-4fef-aa2f-f8df94c1fc08","source":"a1eec96f-94eb-47f0-a810-c48827d16ede","target":"4d2c1400-6476-4628-95eb-b2aaf0660ef4","agreement":true,"isActive":true,"date":1702330909584,"kind":"Connector","isSelected":false,"intensity":3,"isDeletable":true,"isOver":false,"isBidirectional":false,"eventLog":[{"time":1702330909584,"type":"create connection"}]},{"id":"36d9e29f-384f-4f73-bd79-f2418c5338b6","source":"a1eec96f-94eb-47f0-a810-c48827d16ede","target":"f0287fc0-45ba-4857-b146-a7859af80ee8","agreement":true,"isActive":true,"date":1702330911741,"kind":"Connector","isSelected":false,"intensity":3,"isDeletable":true,"isOver":false,"isBidirectional":false,"eventLog":[{"time":1702330911741,"type":"create connection"}]},{"id":"65373774-a39a-4171-8582-4fc2f51cdfe2","source":"f0287fc0-45ba-4857-b146-a7859af80ee8","target":"da4f9aa4-42dd-4950-8131-c3d52d8381cc","agreement":true,"isActive":true,"date":1702330914499,"kind":"Connector","isSelected":false,"intensity":6,"isDeletable":true,"isOver":false,"isBidirectional":false,"eventLog":[{"time":1702330914499,"type":"create connection"},{"time":1702330915643,"type":"selected","value":1},{"time":1702330918066,"type":"change intensity of connector","value":6},{"time":1702330918066,"type":"selected","value":0}]},{"id":"80e49f09-ca0c-46a1-8a1a-5c3df098f37d","source":"83bab52f-e277-4b0a-873e-d18b310c6265","target":"f0287fc0-45ba-4857-b146-a7859af80ee8","agreement":true,"isActive":true,"date":1702330921972,"kind":"Connector","isSelected":false,"intensity":6,"isDeletable":true,"isOver":false,"isBidirectional":false,"eventLog":[{"time":1702330921972,"type":"create connection"},{"time":1702330922785,"type":"selected","value":1},{"time":1702330924465,"type":"change intensity of connector","value":6},{"time":1702330924465,"type":"selected","value":0}]},{"id":"339021d6-ccb7-49de-b9f0-c0bd8892495c","source":"630c66a7-3fa6-48c4-ae80-b371aaa134b2","target":"f0287fc0-45ba-4857-b146-a7859af80ee8","agreement":true,"isActive":true,"date":1702330926566,"kind":"Connector","isSelected":false,"intensity":6,"isDeletable":true,"isOver":false,"isBidirectional":false,"eventLog":[{"time":1702330926566,"type":"create connection"},{"time":1702330927228,"type":"selected","value":1},{"time":1702330928897,"type":"change intensity of connector","value":6},{"time":1702330928897,"type":"selected","value":0}]},{"id":"294c6b95-7f81-4939-868e-ffc4e8f128a2","source":"43fe5882-6daf-4f95-be8e-9ef642440c4c","target":"4d2c1400-6476-4628-95eb-b2aaf0660ef4","agreement":true,"isActive":true,"date":1702330932353,"kind":"Connector","isSelected":false,"intensity":6,"isDeletable":true,"isOver":false,"isBidirectional":false,"eventLog":[{"time":1702330932353,"type":"create connection"},{"time":1702330933242,"type":"selected","value":1},{"time":1702330934891,"type":"change intensity of connector","value":6},{"time":1702330934891,"type":"selected","value":0}]},{"id":"a517c2cb-e684-44b8-9a4e-3f0bc6ab7a87","source":"da4f9aa4-42dd-4950-8131-c3d52d8381cc","target":"4d2c1400-6476-4628-95eb-b2aaf0660ef4","agreement":true,"isActive":true,"date":1702330937686,"kind":"Connector","isSelected":false,"intensity":6,"isDeletable":true,"isOver":false,"isBidirectional":false,"eventLog":[{"time":1702330937686,"type":"create connection"},{"time":1702330938629,"type":"selected","value":1},{"time":1702330940620,"type":"change intensity of connector","value":6},{"time":1702330940620,"type":"selected","value":0}]}],"currentID":["a517c2cb-e684-44b8-9a4e-3f0bc6ab7a87"],"currentNode":{},"hasSelectedNode":[false],"currentConnector":{"id":["a517c2cb-e684-44b8-9a4e-3f0bc6ab7a87"],"value":{},"source":["da4f9aa4-42dd-4950-8131-c3d52d8381cc"],"target":["4d2c1400-6476-4628-95eb-b2aaf0660ef4"],"agreement":[true],"isActive":[true],"date":[1702330937686],"kind":["Connector"],"isSelected":[false],"intensity":[6],"isDeletable":[true],"isOver":[false],"isBidirectional":[false],"eventLog":[{"time":1702330937686,"type":"create connection"},{"time":1702330938629,"type":"selected","value":1},{"time":1702330940620,"type":"change intensity of connector","value":6},{"time":1702330940620,"type":"selected","value":0}]},"hasSelectedConnector":[true],"readyToMove":[false],"isIncoming":[false],"hasElementMoved":[false]}
